dlispy/Component.py
dlispy/LogicalFile.py
dlispy/LogicalRecord.py
dlispy/LogicalRecordSegment.py
dlispy/RCReader.py
dlispy/StorageUnitLabel.py
dlispy/VisibleRecord.py
dlispy/__init__.py
dlispy/common.py
dlispy/core.py
dlispy/logging.ini
dlispy/tests/__init__.py
dlispy/tests/test_basic.py
dlispy-0.0.2.dist-info/METADATA
dlispy-0.0.2.dist-info/RECORD
dlispy-0.0.2.dist-info/WHEEL
dlispy-0.0.2.dist-info/top_level.txt
