Metadata-Version: 2.1
Name: dlispy
Version: 0.0.2
Summary: A python library to parse DLIS file
Home-page: https://github.com/teradata/dlispy
License: BSD-3-Clause
Platform: any
Classifier: Programming Language :: Python :: 3.5
Classifier: Programming Language :: Python :: 3.6
Classifier: License :: OSI Approved :: BSD License
Classifier: Operating System :: OS Independent
Requires-Python: >=3.5
Requires-Dist: atomicwrites (==1.1.5)
Requires-Dist: attrs (==18.1.0)
Requires-Dist: click (==6.7)
Requires-Dist: more-itertools (==4.3.0)
Requires-Dist: pluggy (==0.7.1)
Requires-Dist: py (==1.5.4)
Requires-Dist: pytest (==3.7.1)
Requires-Dist: six (==1.11.0)
